{
  "version": 2,
  "generatedAt": "2026-07-19T15:18:37.272Z",
  "subjects": [
    {
      "id": "math",
      "name": "Математика",
      "examType": "OGE",
      "topicsCount": 10
    },
    {
      "id": "rus",
      "name": "Русский язык",
      "examType": "OGE",
      "topicsCount": 5
    },
    {
      "id": "phys",
      "name": "Физика",
      "examType": "OGE",
      "topicsCount": 4
    },
    {
      "id": "test",
      "name": "Тест",
      "examType": "OGE",
      "topicsCount": 1
    }
  ],
  "topics": [
    {
      "id": "math_tables",
      "subjectId": "math",
      "name": "Работа с таблицами и диаграммами",
      "taskNumberInExam": 1
    },
    {
      "id": "math_calc",
      "subjectId": "math",
      "name": "Вычисления и преобразования выражений",
      "taskNumberInExam": 2
    },
    {
      "id": "math_fractions",
      "subjectId": "math",
      "name": "Дроби и проценты",
      "taskNumberInExam": 3
    },
    {
      "id": "math_eq",
      "subjectId": "math",
      "name": "Уравнения и неравенства",
      "taskNumberInExam": 4
    },
    {
      "id": "math_seq",
      "subjectId": "math",
      "name": "Числовые последовательности и прогрессии",
      "taskNumberInExam": 5
    },
    {
      "id": "math_word",
      "subjectId": "math",
      "name": "Текстовые задачи",
      "taskNumberInExam": 6
    },
    {
      "id": "math_func",
      "subjectId": "math",
      "name": "Функции и графики",
      "taskNumberInExam": 7
    },
    {
      "id": "math_geo",
      "subjectId": "math",
      "name": "Планиметрия",
      "taskNumberInExam": 8
    },
    {
      "id": "math_prob",
      "subjectId": "math",
      "name": "Теория вероятностей и статистика",
      "taskNumberInExam": 9
    },
    {
      "id": "math_real",
      "subjectId": "math",
      "name": "Реальная математика (практико-ориентированные задачи)",
      "taskNumberInExam": 10
    },
    {
      "id": "rus_orfo",
      "subjectId": "rus",
      "name": "Орфография",
      "taskNumberInExam": 1
    },
    {
      "id": "rus_punct",
      "subjectId": "rus",
      "name": "Пунктуация",
      "taskNumberInExam": 2
    },
    {
      "id": "rus_lexic",
      "subjectId": "rus",
      "name": "Лексика и фразеология",
      "taskNumberInExam": 3
    },
    {
      "id": "rus_syntax",
      "subjectId": "rus",
      "name": "Синтаксический анализ",
      "taskNumberInExam": 4
    },
    {
      "id": "rus_speech",
      "subjectId": "rus",
      "name": "Средства выразительности речи",
      "taskNumberInExam": 5
    },
    {
      "id": "phys_mech",
      "subjectId": "phys",
      "name": "Механика",
      "taskNumberInExam": 1
    },
    {
      "id": "phys_thermal",
      "subjectId": "phys",
      "name": "Тепловые явления",
      "taskNumberInExam": 2
    },
    {
      "id": "phys_electro",
      "subjectId": "phys",
      "name": "Электродинамика",
      "taskNumberInExam": 3
    },
    {
      "id": "phys_optics",
      "subjectId": "phys",
      "name": "Оптика и квантовые явления",
      "taskNumberInExam": 4
    },
    {
      "id": "test_test",
      "subjectId": "test",
      "name": "Тест",
      "taskNumberInExam": 1
    }
  ],
  "questions": [
    {
      "id": "mt_tables_1",
      "topicId": "math_tables",
      "examType": "OGE",
      "text": "На диаграмме показана температура воздуха по дням недели. В какой день недели температура была наибольшей?",
      "imageUrl": null,
      "optionIds": [
        "a",
        "b",
        "c",
        "d"
      ],
      "optionTexts": [
        "Понедельник",
        "Среда",
        "Пятница",
        "Суббота"
      ],
      "correctOptionId": "c",
      "correctShortAnswer": null,
      "explanation": "На диаграмме столбец за пятницу самый высокий среди всех дней недели.",
      "difficulty": 1
    },
    {
      "id": "mt_tables_2",
      "topicId": "math_tables",
      "examType": "OGE",
      "text": "В таблице приведены цены на билеты в кино в будни и выходные. Сколько будет стоить 3 билета в субботу, если один стоит 350 рублей?",
      "imageUrl": null,
      "optionIds": [],
      "optionTexts": [],
      "correctOptionId": null,
      "correctShortAnswer": "1050",
      "explanation": "350 × 3 = 1050 рублей.",
      "difficulty": 1
    },
    {
      "id": "mt_tables_3",
      "topicId": "math_tables",
      "examType": "OGE",
      "text": "По графику видно, что курс валюты за неделю вырос с 90 до 96 рублей. На сколько рублей вырос курс?",
      "imageUrl": null,
      "optionIds": [],
      "optionTexts": [],
      "correctOptionId": null,
      "correctShortAnswer": "6",
      "explanation": "96 − 90 = 6 рублей.",
      "difficulty": 1
    },
    {
      "id": "mt_calc_1",
      "topicId": "math_calc",
      "examType": "OGE",
      "text": "Найдите значение выражения (2/5 + 1/10) × 20",
      "imageUrl": null,
      "optionIds": [
        "a",
        "b",
        "c",
        "d"
      ],
      "optionTexts": [
        "9",
        "10",
        "11",
        "12"
      ],
      "correctOptionId": "b",
      "correctShortAnswer": null,
      "explanation": "2/5 + 1/10 = 0.5. Далее 0.5 × 20 = 10.",
      "difficulty": 1
    },
    {
      "id": "mt_calc_2",
      "topicId": "math_calc",
      "examType": "OGE",
      "text": "Вычислите: 3.7 × 10² − 15",
      "imageUrl": null,
      "optionIds": [],
      "optionTexts": [],
      "correctOptionId": null,
      "correctShortAnswer": "355",
      "explanation": "3.7 × 100 = 370. 370 − 15 = 355.",
      "difficulty": 1
    },
    {
      "id": "mt_calc_3",
      "topicId": "math_calc",
      "examType": "OGE",
      "text": "Найдите значение выражения √49 + √16",
      "imageUrl": null,
      "optionIds": [],
      "optionTexts": [],
      "correctOptionId": null,
      "correctShortAnswer": "11",
      "explanation": "√49 = 7, √16 = 4. 7 + 4 = 11.",
      "difficulty": 1
    },
    {
      "id": "mt_fractions_1",
      "topicId": "math_fractions",
      "examType": "OGE",
      "text": "Товар стоил 2000 рублей. Цену снизили на 15%. Сколько стал стоить товар?",
      "imageUrl": null,
      "optionIds": [
        "a",
        "b",
        "c",
        "d"
      ],
      "optionTexts": [
        "1700 руб.",
        "1800 руб.",
        "1850 руб.",
        "1900 руб."
      ],
      "correctOptionId": "b",
      "correctShortAnswer": null,
      "explanation": "15% от 2000 — это 300 рублей. 2000 − 300 = 1700 рублей.",
      "difficulty": 1
    },
    {
      "id": "mt_fractions_2",
      "topicId": "math_fractions",
      "examType": "OGE",
      "text": "Найдите число, если 40% этого числа равны 68.",
      "imageUrl": null,
      "optionIds": [],
      "optionTexts": [],
      "correctOptionId": null,
      "correctShortAnswer": "170",
      "explanation": "68 / 0.4 = 170.",
      "difficulty": 2
    },
    {
      "id": "mt_fractions_3",
      "topicId": "math_fractions",
      "examType": "OGE",
      "text": "Смешали 3 кг конфет по 200 руб/кг и 2 кг по 300 руб/кг. Найдите среднюю цену смеси за 1 кг.",
      "imageUrl": null,
      "optionIds": [],
      "optionTexts": [],
      "correctOptionId": null,
      "correctShortAnswer": "240",
      "explanation": "(3×200 + 2×300) / 5 = 1200/5 = 240.",
      "difficulty": 2
    },
    {
      "id": "mt_eq_1",
      "topicId": "math_eq",
      "examType": "OGE",
      "text": "Решите уравнение: 3x − 7 = 2x + 5. Укажите корень.",
      "imageUrl": null,
      "optionIds": [],
      "optionTexts": [],
      "correctOptionId": null,
      "correctShortAnswer": "12",
      "explanation": "3x − 2x = 5 + 7 → x = 12.",
      "difficulty": 1
    },
    {
      "id": "mt_eq_2",
      "topicId": "math_eq",
      "examType": "OGE",
      "text": "Решите неравенство 2x + 3 > 11. Укажите наименьшее целое решение.",
      "imageUrl": null,
      "optionIds": [
        "a",
        "b",
        "c",
        "d"
      ],
      "optionTexts": [
        "3",
        "4",
        "5",
        "6"
      ],
      "correctOptionId": "c",
      "correctShortAnswer": null,
      "explanation": "2x > 8 → x > 4. Наименьшее целое число, большее 4, — это 5.",
      "difficulty": 2
    },
    {
      "id": "mt_eq_3",
      "topicId": "math_eq",
      "examType": "OGE",
      "text": "Решите уравнение x² − 9 = 0. Укажите больший корень.",
      "imageUrl": null,
      "optionIds": [],
      "optionTexts": [],
      "correctOptionId": null,
      "correctShortAnswer": "3",
      "explanation": "x² = 9 → x = ±3. Больший корень — 3.",
      "difficulty": 2
    },
    {
      "id": "mt_seq_1",
      "topicId": "math_seq",
      "examType": "OGE",
      "text": "Арифметическая прогрессия задана условиями a₁ = 5, d = 3. Найдите a₁₀.",
      "imageUrl": null,
      "optionIds": [],
      "optionTexts": [],
      "correctOptionId": null,
      "correctShortAnswer": "32",
      "explanation": "aₙ = a₁ + (n−1)d = 5 + 9×3 = 32.",
      "difficulty": 2
    },
    {
      "id": "mt_seq_2",
      "topicId": "math_seq",
      "examType": "OGE",
      "text": "Найдите сумму первых пяти членов геометрической прогрессии 2, 4, 8, 16, ...",
      "imageUrl": null,
      "optionIds": [
        "a",
        "b",
        "c",
        "d"
      ],
      "optionTexts": [
        "30",
        "62",
        "64",
        "31"
      ],
      "correctOptionId": "b",
      "correctShortAnswer": null,
      "explanation": "2+4+8+16+32 = 62.",
      "difficulty": 2
    },
    {
      "id": "mt_seq_3",
      "topicId": "math_seq",
      "examType": "OGE",
      "text": "Найдите d арифметической прогрессии, если a₁ = 2, a₅ = 18.",
      "imageUrl": null,
      "optionIds": [],
      "optionTexts": [],
      "correctOptionId": null,
      "correctShortAnswer": "4",
      "explanation": "a₅ = a₁ + 4d → 18 = 2 + 4d → d = 4.",
      "difficulty": 2
    },
    {
      "id": "mt_word_1",
      "topicId": "math_word",
      "examType": "OGE",
      "text": "Велосипедист проехал 60 км за 4 часа. С какой средней скоростью он двигался?",
      "imageUrl": null,
      "optionIds": [],
      "optionTexts": [],
      "correctOptionId": null,
      "correctShortAnswer": "15",
      "explanation": "60 / 4 = 15 км/ч.",
      "difficulty": 1
    },
    {
      "id": "mt_word_2",
      "topicId": "math_word",
      "examType": "OGE",
      "text": "Первый рабочий выполняет заказ за 6 дней, второй — за 12 дней. За сколько дней они выполнят заказ вместе?",
      "imageUrl": null,
      "optionIds": [
        "a",
        "b",
        "c",
        "d"
      ],
      "optionTexts": [
        "3",
        "4",
        "5",
        "6"
      ],
      "correctOptionId": "b",
      "correctShortAnswer": null,
      "explanation": "1/6 + 1/12 = 1/4 в день. Время = 4 дня.",
      "difficulty": 2
    },
    {
      "id": "mt_word_3",
      "topicId": "math_word",
      "examType": "OGE",
      "text": "Поезд прошёл 350 км за 5 часов, а затем ещё 150 км за 3 часа. Найдите среднюю скорость поезда за всё время.",
      "imageUrl": null,
      "optionIds": [],
      "optionTexts": [],
      "correctOptionId": null,
      "correctShortAnswer": "62.5",
      "explanation": "Общий путь 500 км, время 8 часов. 500/8 = 62.5 км/ч.",
      "difficulty": 2
    },
    {
      "id": "mt_func_1",
      "topicId": "math_func",
      "examType": "OGE",
      "text": "График функции y = 2x − 3 пересекает ось Oy в точке с координатой y, равной:",
      "imageUrl": null,
      "optionIds": [
        "a",
        "b",
        "c",
        "d"
      ],
      "optionTexts": [
        "-3",
        "0",
        "2",
        "3"
      ],
      "correctOptionId": "a",
      "correctShortAnswer": null,
      "explanation": "При x = 0 значение y = 2×0 − 3 = −3.",
      "difficulty": 1
    },
    {
      "id": "mt_func_2",
      "topicId": "math_func",
      "examType": "OGE",
      "text": "Найдите значение функции y = x² − 4x + 3 при x = 1.",
      "imageUrl": null,
      "optionIds": [],
      "optionTexts": [],
      "correctOptionId": null,
      "correctShortAnswer": "0",
      "explanation": "1 − 4 + 3 = 0.",
      "difficulty": 1
    },
    {
      "id": "mt_func_3",
      "topicId": "math_func",
      "examType": "OGE",
      "text": "При каком значении x функция y = 5x − 10 обращается в ноль?",
      "imageUrl": null,
      "optionIds": [],
      "optionTexts": [],
      "correctOptionId": null,
      "correctShortAnswer": "2",
      "explanation": "5x − 10 = 0 → x = 2.",
      "difficulty": 1
    },
    {
      "id": "mt_geo_1",
      "topicId": "math_geo",
      "examType": "OGE",
      "text": "Сумма углов треугольника равна:",
      "imageUrl": null,
      "optionIds": [
        "a",
        "b",
        "c"
      ],
      "optionTexts": [
        "90°",
        "180°",
        "360°"
      ],
      "correctOptionId": "b",
      "correctShortAnswer": null,
      "explanation": "Сумма внутренних углов любого треугольника на плоскости всегда равна 180°.",
      "difficulty": 1
    },
    {
      "id": "mt_geo_2",
      "topicId": "math_geo",
      "examType": "OGE",
      "text": "Катеты прямоугольного треугольника равны 6 и 8. Найдите гипотенузу.",
      "imageUrl": null,
      "optionIds": [],
      "optionTexts": [],
      "correctOptionId": null,
      "correctShortAnswer": "10",
      "explanation": "По теореме Пифагора: √(36+64) = 10.",
      "difficulty": 1
    },
    {
      "id": "mt_geo_3",
      "topicId": "math_geo",
      "examType": "OGE",
      "text": "Найдите площадь прямоугольника со сторонами 7 см и 5 см.",
      "imageUrl": null,
      "optionIds": [],
      "optionTexts": [],
      "correctOptionId": null,
      "correctShortAnswer": "35",
      "explanation": "Площадь прямоугольника = произведение сторон: 7×5 = 35 см².",
      "difficulty": 1
    },
    {
      "id": "mt_prob_1",
      "topicId": "math_prob",
      "examType": "OGE",
      "text": "В классе 25 учеников, среди них два близнеца. Класс случайным образом делят на две группы по 12 и 13 человек. Найдите вероятность того, что близнецы окажутся в одной группе.",
      "imageUrl": null,
      "optionIds": [
        "a",
        "b",
        "c",
        "d"
      ],
      "optionTexts": [
        "0.46",
        "0.5",
        "0.52",
        "0.48"
      ],
      "correctOptionId": "a",
      "correctShortAnswer": null,
      "explanation": "P = (12/25)×(11/24) + (13/25)×(12/24) ≈ 0.46.",
      "difficulty": 2
    },
    {
      "id": "mt_prob_2",
      "topicId": "math_prob",
      "examType": "OGE",
      "text": "В коробке 4 красных и 6 синих шаров. Найдите вероятность того, что наугад вынутый шар красный.",
      "imageUrl": null,
      "optionIds": [],
      "optionTexts": [],
      "correctOptionId": null,
      "correctShortAnswer": "0.4",
      "explanation": "P = 4 / (4+6) = 0.4.",
      "difficulty": 1
    },
    {
      "id": "mt_prob_3",
      "topicId": "math_prob",
      "examType": "OGE",
      "text": "Монету бросают дважды. Найдите вероятность того, что оба раза выпадет орёл.",
      "imageUrl": null,
      "optionIds": [],
      "optionTexts": [],
      "correctOptionId": null,
      "correctShortAnswer": "0.25",
      "explanation": "P = 0.5 × 0.5 = 0.25.",
      "difficulty": 2
    },
    {
      "id": "mt_real_1",
      "topicId": "math_real",
      "examType": "OGE",
      "text": "Тариф на такси: посадка 100 руб. + 20 руб. за км. Сколько будет стоить поездка на 12 км?",
      "imageUrl": null,
      "optionIds": [],
      "optionTexts": [],
      "correctOptionId": null,
      "correctShortAnswer": "340",
      "explanation": "100 + 20×12 = 340 рублей.",
      "difficulty": 1
    },
    {
      "id": "mt_real_2",
      "topicId": "math_real",
      "examType": "OGE",
      "text": "Комната имеет форму прямоугольника 4 м × 5 м. Сколько потребуется банок краски, если одной хватает на 10 м²?",
      "imageUrl": null,
      "optionIds": [
        "a",
        "b",
        "c",
        "d"
      ],
      "optionTexts": [
        "1",
        "2",
        "3",
        "4"
      ],
      "correctOptionId": "b",
      "correctShortAnswer": null,
      "explanation": "Площадь пола 4×5=20 м². 20 / 10 = 2 банки.",
      "difficulty": 1
    },
    {
      "id": "mt_real_3",
      "topicId": "math_real",
      "examType": "OGE",
      "text": "Тариф на мобильную связь: 300 руб. абонплата + 3 руб. за минуту сверх 200 минут. Сколько заплатит абонент при 250 минутах разговора?",
      "imageUrl": null,
      "optionIds": [],
      "optionTexts": [],
      "correctOptionId": null,
      "correctShortAnswer": "450",
      "explanation": "300 + (250−200)×3 = 450 рублей.",
      "difficulty": 2
    },
    {
      "id": "ru_orfo_1",
      "topicId": "rus_orfo",
      "examType": "OGE",
      "text": "В каком слове пропущена буква Е: пр…образовать, пр…града, пр…рвать?",
      "imageUrl": null,
      "optionIds": [
        "a",
        "b",
        "c"
      ],
      "optionTexts": [
        "пр_образовать",
        "пр_града",
        "пр_рвать"
      ],
      "correctOptionId": "b",
      "correctShortAnswer": null,
      "explanation": "«Преграда» пишется с «пре-» в значении «через, очень».",
      "difficulty": 1
    },
    {
      "id": "ru_orfo_2",
      "topicId": "rus_orfo",
      "examType": "OGE",
      "text": "В каком слове пишется НН: жаре...ый картофель, серебря...ый браслет, ветре...ый день?",
      "imageUrl": null,
      "optionIds": [
        "a",
        "b",
        "c"
      ],
      "optionTexts": [
        "жаре_ый",
        "серебря_ый",
        "ветре_ый"
      ],
      "correctOptionId": "b",
      "correctShortAnswer": null,
      "explanation": "«Серебряный» — суффикс -ян-, прилагательное от существительного, пишется с одной Н.",
      "difficulty": 1
    },
    {
      "id": "ru_orfo_3",
      "topicId": "rus_orfo",
      "examType": "OGE",
      "text": "Укажите слово, где после шипящей пишется буква О: ш...рох, ш...пот, крыж...вник.",
      "imageUrl": null,
      "optionIds": [],
      "optionTexts": [],
      "correctOptionId": null,
      "correctShortAnswer": "крыжовник",
      "explanation": "В корне «крыжовник» после шипящей под ударением пишется О — словарное исключение.",
      "difficulty": 1
    },
    {
      "id": "ru_punct_1",
      "topicId": "rus_punct",
      "examType": "OGE",
      "text": "Нужна ли запятая: «Собираясь в поход мы тщательно проверили снаряжение»?",
      "imageUrl": null,
      "optionIds": [
        "a",
        "b"
      ],
      "optionTexts": [
        "Да, после «поход»",
        "Нет, запятая не нужна"
      ],
      "correctOptionId": "a",
      "correctShortAnswer": null,
      "explanation": "Деепричастный оборот «Собираясь в поход» обособляется запятой.",
      "difficulty": 1
    },
    {
      "id": "ru_punct_2",
      "topicId": "rus_punct",
      "examType": "OGE",
      "text": "Сколько запятых нужно в предложении «Дождь который шёл всю ночь наконец прекратился»?",
      "imageUrl": null,
      "optionIds": [],
      "optionTexts": [],
      "correctOptionId": null,
      "correctShortAnswer": "2",
      "explanation": "Придаточная часть «который шёл всю ночь» выделяется запятыми с двух сторон.",
      "difficulty": 2
    },
    {
      "id": "ru_punct_3",
      "topicId": "rus_punct",
      "examType": "OGE",
      "text": "Нужно ли тире: «Москва — столица России»?",
      "imageUrl": null,
      "optionIds": [
        "a",
        "b"
      ],
      "optionTexts": [
        "Да",
        "Нет"
      ],
      "correctOptionId": "a",
      "correctShortAnswer": null,
      "explanation": "Тире ставится между подлежащим и сказуемым, выраженными существительными в именительном падеже.",
      "difficulty": 1
    },
    {
      "id": "ru_lexic_1",
      "topicId": "rus_lexic",
      "examType": "OGE",
      "text": "Подберите синоним к слову «беспечный»",
      "imageUrl": null,
      "optionIds": [
        "a",
        "b",
        "c"
      ],
      "optionTexts": [
        "легкомысленный",
        "аккуратный",
        "трудолюбивый"
      ],
      "correctOptionId": "a",
      "correctShortAnswer": null,
      "explanation": "«Беспечный» и «легкомысленный» оба означают отсутствие заботы о последствиях.",
      "difficulty": 1
    },
    {
      "id": "ru_lexic_2",
      "topicId": "rus_lexic",
      "examType": "OGE",
      "text": "Укажите фразеологизм со значением «бездельничать»",
      "imageUrl": null,
      "optionIds": [
        "a",
        "b",
        "c"
      ],
      "optionTexts": [
        "бить баклуши",
        "держать слово",
        "вешать нос"
      ],
      "correctOptionId": "a",
      "correctShortAnswer": null,
      "explanation": "«Бить баклуши» — устойчивое выражение со значением «ничего не делать».",
      "difficulty": 1
    },
    {
      "id": "ru_syntax_1",
      "topicId": "rus_syntax",
      "examType": "OGE",
      "text": "Определите вид связи в словосочетании «читать книгу»",
      "imageUrl": null,
      "optionIds": [
        "a",
        "b",
        "c"
      ],
      "optionTexts": [
        "управление",
        "согласование",
        "примыкание"
      ],
      "correctOptionId": "a",
      "correctShortAnswer": null,
      "explanation": "В управлении зависимое слово ставится в определённом падеже — здесь винительном.",
      "difficulty": 2
    },
    {
      "id": "ru_syntax_2",
      "topicId": "rus_syntax",
      "examType": "OGE",
      "text": "Сколько грамматических основ в предложении «Ветер утих, и на небе показалось солнце»?",
      "imageUrl": null,
      "optionIds": [],
      "optionTexts": [],
      "correctOptionId": null,
      "correctShortAnswer": "2",
      "explanation": "Две основы: «ветер утих» и «солнце показалось», предложение сложносочинённое.",
      "difficulty": 2
    },
    {
      "id": "ru_speech_1",
      "topicId": "rus_speech",
      "examType": "OGE",
      "text": "Как называется троп в выражении «золотые руки»?",
      "imageUrl": null,
      "optionIds": [
        "a",
        "b",
        "c"
      ],
      "optionTexts": [
        "метафора",
        "гипербола",
        "олицетворение"
      ],
      "correctOptionId": "a",
      "correctShortAnswer": null,
      "explanation": "Скрытое сравнение по признаку ценности — это метафора.",
      "difficulty": 1
    },
    {
      "id": "ru_speech_2",
      "topicId": "rus_speech",
      "examType": "OGE",
      "text": "Какое средство выразительности используется во фразе «миллион алых роз»?",
      "imageUrl": null,
      "optionIds": [
        "a",
        "b",
        "c"
      ],
      "optionTexts": [
        "гипербола",
        "литота",
        "антитеза"
      ],
      "correctOptionId": "a",
      "correctShortAnswer": null,
      "explanation": "Явное преувеличение количества — гипербола.",
      "difficulty": 1
    },
    {
      "id": "ph_mech_1",
      "topicId": "phys_mech",
      "examType": "OGE",
      "text": "Тело равномерно движется со скоростью 5 м/с. Какой путь оно пройдёт за 20 секунд?",
      "imageUrl": null,
      "optionIds": [],
      "optionTexts": [],
      "correctOptionId": null,
      "correctShortAnswer": "100",
      "explanation": "s = v×t = 5×20 = 100 метров.",
      "difficulty": 1
    },
    {
      "id": "ph_mech_2",
      "topicId": "phys_mech",
      "examType": "OGE",
      "text": "Чему равна масса тела, если сила 20 Н сообщает ему ускорение 4 м/с²?",
      "imageUrl": null,
      "optionIds": [],
      "optionTexts": [],
      "correctOptionId": null,
      "correctShortAnswer": "5",
      "explanation": "По второму закону Ньютона m = F/a = 20/4 = 5 кг.",
      "difficulty": 2
    },
    {
      "id": "ph_mech_3",
      "topicId": "phys_mech",
      "examType": "OGE",
      "text": "Какая величина измеряется в ньютонах?",
      "imageUrl": null,
      "optionIds": [
        "a",
        "b",
        "c"
      ],
      "optionTexts": [
        "Сила",
        "Масса",
        "Скорость"
      ],
      "correctOptionId": "a",
      "correctShortAnswer": null,
      "explanation": "Ньютон (Н) — единица измерения силы в СИ.",
      "difficulty": 1
    },
    {
      "id": "ph_thermal_1",
      "topicId": "phys_thermal",
      "examType": "OGE",
      "text": "Сколько энергии нужно, чтобы нагреть 2 кг воды на 10°C (удельная теплоёмкость воды 4200 Дж/(кг·°C))?",
      "imageUrl": null,
      "optionIds": [],
      "optionTexts": [],
      "correctOptionId": null,
      "correctShortAnswer": "84000",
      "explanation": "Q = c×m×ΔT = 4200×2×10 = 84000 Дж.",
      "difficulty": 2
    },
    {
      "id": "ph_thermal_2",
      "topicId": "phys_thermal",
      "examType": "OGE",
      "text": "При какой температуре по шкале Цельсия кипит вода при нормальном атмосферном давлении?",
      "imageUrl": null,
      "optionIds": [],
      "optionTexts": [],
      "correctOptionId": null,
      "correctShortAnswer": "100",
      "explanation": "Температура кипения воды при нормальном давлении — 100°C.",
      "difficulty": 1
    },
    {
      "id": "ph_electro_1",
      "topicId": "phys_electro",
      "examType": "OGE",
      "text": "Найдите силу тока в цепи, если напряжение 12 В, а сопротивление 4 Ом.",
      "imageUrl": null,
      "optionIds": [],
      "optionTexts": [],
      "correctOptionId": null,
      "correctShortAnswer": "3",
      "explanation": "По закону Ома I = U/R = 12/4 = 3 А.",
      "difficulty": 1
    },
    {
      "id": "ph_electro_2",
      "topicId": "phys_electro",
      "examType": "OGE",
      "text": "Как называется единица измерения электрического сопротивления?",
      "imageUrl": null,
      "optionIds": [
        "a",
        "b",
        "c"
      ],
      "optionTexts": [
        "Ом",
        "Ампер",
        "Вольт"
      ],
      "correctOptionId": "a",
      "correctShortAnswer": null,
      "explanation": "Ом — единица измерения электрического сопротивления.",
      "difficulty": 1
    },
    {
      "id": "ph_optics_1",
      "topicId": "phys_optics",
      "examType": "OGE",
      "text": "Как называется явление изменения направления света при переходе из одной среды в другую?",
      "imageUrl": null,
      "optionIds": [
        "a",
        "b",
        "c"
      ],
      "optionTexts": [
        "Преломление",
        "Отражение",
        "Дифракция"
      ],
      "correctOptionId": "a",
      "correctShortAnswer": null,
      "explanation": "Изменение направления луча на границе двух сред называется преломлением света.",
      "difficulty": 1
    },
    {
      "id": "test_test_1",
      "topicId": "test_test",
      "examType": "OGE",
      "text": "В каком слове пропущена буква Е: пр…образовать, пр…града, пр…рвать?",
      "imageUrl": null,
      "optionIds": [
        "a",
        "b",
        "c"
      ],
      "optionTexts": [
        "пр_образовать",
        "пр_града",
        "пр_рвать"
      ],
      "correctOptionId": "b",
      "correctShortAnswer": null,
      "explanation": "«Преграда» пишется с «пре-» в значении «через, очень».",
      "difficulty": 1
    }
  ]
}